coco_microsoft_bot_framework/__init__.py
coco_microsoft_bot_framework/coco_microsoft_bot_framework.py
coco_microsoft_bot_framework-0.0.1.dist-info/LICENSE
coco_microsoft_bot_framework-0.0.1.dist-info/METADATA
coco_microsoft_bot_framework-0.0.1.dist-info/WHEEL
coco_microsoft_bot_framework-0.0.1.dist-info/top_level.txt
coco_microsoft_bot_framework-0.0.1.dist-info/RECORD
