Metadata-Version: 2.1
Name: coco-microsoft-bot-framework
Version: 0.0.1
Summary: CoCo(Conversational Components) SDK for using components with Microsoft Bot Framework.
Home-page: https://github.com/conversationalcomponents/coco-microsoft-bot-framework
Author: Victor Vasiliev
Author-email: victor@a-i.com
License: MIT
Platform: UNKNOWN
Classifier: Development Status :: 2 - Pre-Alpha
Classifier: Intended Audience :: Developers
Classifier: Intended Audience :: Education
Classifier: Intended Audience :: Science/Research
Classifier: License :: OSI Approved :: MIT License
Classifier: Programming Language :: Python :: 3
Classifier: Topic :: Software Development :: Libraries
Classifier: Topic :: Software Development :: Libraries :: Python Modules
Requires-Python: >=3.6
Requires-Dist: coco-sdk
Requires-Dist: botbuilder-core
